fogstone/__init__.py
fogstone/__main__.py
fogstone/app.py
fogstone/logic.py
fogstone/models.py
fogstone/settings.py
fogstone/views.py
fogstone/data/index.md
fogstone/static/favicon.ico
fogstone/static/css/bootstrap.min.css
fogstone/static/css/style.css
fogstone/static/fonts/glyphicons-halflings-regular.eot
fogstone/static/fonts/glyphicons-halflings-regular.svg
fogstone/static/fonts/glyphicons-halflings-regular.ttf
fogstone/static/fonts/glyphicons-halflings-regular.woff
fogstone/static/fonts/glyphicons-halflings-regular.woff2
fogstone/templates/base.html
fogstone/templates/page.html
fogstone/templates/search.html
fogstone/templates/partials/footer.html
fogstone/templates/partials/header.html
fogstone/templates/partials/sidebar.html
fogstone/translations/ru/LC_MESSAGES/messages.mo
fogstone/translations/ru/LC_MESSAGES/messages.po
fogstone-0.5.3.dist-info/LICENSE
fogstone-0.5.3.dist-info/METADATA
fogstone-0.5.3.dist-info/WHEEL
fogstone-0.5.3.dist-info/entry_points.txt
fogstone-0.5.3.dist-info/top_level.txt
fogstone-0.5.3.dist-info/RECORD
