Metadata-Version: 2.1
Name: fogstone
Version: 0.5.3
Summary: Simple helpdesk system
Home-page: https://github.com/MC4EP/fogstone
Author: Andriy Kushnir (Orhideous)
Author-email: me@orhideous.name
License: MIT
Platform: any
Classifier: Development Status :: 3 - Alpha
Classifier: Framework :: Flask
Classifier: License :: OSI Approved
Classifier: License :: OSI Approved :: MIT License
Classifier: Operating System :: OS Independent
Classifier: Programming Language :: Python
Classifier: Programming Language :: Python :: 3
Classifier: Programming Language :: Python :: 3.6
Classifier: Programming Language :: Python :: Implementation :: CPython
Classifier: Topic :: Internet :: WWW/HTTP :: WSGI
Classifier: Topic :: Internet :: WWW/HTTP :: WSGI :: Application
Requires-Dist: Flask (==0.12.2)
Requires-Dist: Flask-Babel (==0.11.2)
Requires-Dist: Markdown (==2.6.11)
Requires-Dist: pydantic (==1.5.1)
Requires-Dist: pyembed-markdown (==1.1.0)
Requires-Dist: transliterate (==1.10.0)
Requires-Dist: werkzeug (==0.16.1)
